mlx_bigvgan/__init__.py
mlx_bigvgan/act.py
mlx_bigvgan/alias_free_activation.py
mlx_bigvgan/audio.py
mlx_bigvgan/bigvgan.py
mlx_bigvgan/convert.py
mlx_bigvgan/py.typed
mlx_bigvgan-0.1.1.dist-info/licenses/LICENSE
mlx_bigvgan-0.1.1.dist-info/METADATA
mlx_bigvgan-0.1.1.dist-info/WHEEL
mlx_bigvgan-0.1.1.dist-info/entry_points.txt
mlx_bigvgan-0.1.1.dist-info/top_level.txt
mlx_bigvgan-0.1.1.dist-info/RECORD
