Metadata-Version: 2.4
Name: mlx-bigvgan
Version: 0.1.1
Summary: MLX implementation of BigVGAN
Author: Yrom
License: MIT
Project-URL: Repository, https://github.com/yrom/mlx-bigvgan
Project-URL: Issues, https://github.com/yrom/mlx-bigvgan/issues
Keywords: MLX,BigVGAN
Classifier: Programming Language :: Python :: 3.11
Classifier: License :: OSI Approved :: MIT License
Classifier: Operating System :: MacOS
Requires-Python: >=3.11
License-File: LICENSE
Requires-Dist: mlx>=0.22.1
Requires-Dist: numpy
Requires-Dist: huggingface-hub
Requires-Dist: soundfile
Provides-Extra: test
Requires-Dist: librosa; extra == "test"
Requires-Dist: torchaudio; extra == "test"
Requires-Dist: torch; extra == "test"
Requires-Dist: matplotlib; extra == "test"
Dynamic: license-file
